{
    "V": 2,
    "C": {
        "A": {
            "D": 245,
            "T": [
                [
                    "P",
                    3035395,
                    [
                        { "P": [140.5, -30.35], "I": 0, "T": 0 },
                        { "P": [140.5, -30.35], "I": 21 },
                        { "P": [140.5, -30.35], "I": 33, "T": 0 },
                        { "P": [140.5, -30.35], "I": 45 },
                        { "P": [140.5, -30.35], "I": 51 },
                        { "P": [140.5, -30.35], "I": 58, "T": 0 },
                        { "P": [140.5, -30.35], "I": 101 },
                        { "P": [140.5, -30.35], "I": 107 },
                        { "P": [140.5, -30.35], "I": 114, "T": 0 },
                        { "P": [30.35, -30.35], "I": 159, "T": 0 },
                        { "P": [30.35, -30.35], "I": 166, "T": 0 }
                    ]
                ],
                [
                    "Scale",
                    3035395,
                    [
                        { "P": [0.9, 0.9], "I": 0, "T": 0 },
                        { "P": [0.9, 0.9], "I": 21 },
                        { "P": [0.9, 0.9], "I": 33, "T": 0 },
                        { "P": [0.9, 0.9], "I": 45 },
                        { "P": [0.75, 0.75], "I": 51 },
                        { "P": [0.9, 0.9], "I": 58, "T": 0 },
                        { "P": [0.9, 0.9], "I": 101 },
                        { "P": [0.75, 0.75], "I": 107 },
                        { "P": [0.9, 0.9], "I": 114, "T": 0 },
                        { "P": [1, 1], "I": 159, "T": 0 },
                        { "P": [1, 1], "I": 166, "T": 0 }
                    ]
                ],
                [
                    "Alpha",
                    3035395,
                    [
                        { "V": 0, "I": 0, "T": 0 },
                        { "V": 0, "I": 21 },
                        { "V": 255, "I": 33, "T": 0 },
                        { "V": 255, "I": 45 },
                        { "V": 255, "I": 51 },
                        { "V": 255, "I": 58, "T": 0 },
                        { "V": 255, "I": 101 },
                        { "V": 255, "I": 107 },
                        { "V": 255, "I": 114, "T": 0 },
                        { "V": 0, "I": 159, "T": 0 },
                        { "V": 0, "I": 166, "T": 0 }
                    ]
                ],
                [
                    "P",
                    3035393,
                    [
                        { "P": [170.6, -30.35], "I": 0, "T": 0 },
                        { "P": [170.6, -30.35], "I": 9 },
                        { "P": [140.5, -30.35], "I": 21 },
                        { "P": [140.5, -30.35], "I": 33, "T": 0 },
                        { "P": [30.35, -30.35], "I": 34, "T": 0 }
                    ]
                ],
                [
                    "Scale",
                    3035393,
                    [
                        { "P": [0.585, 0.585], "I": 0, "T": 0 },
                        { "P": [0.585, 0.585], "I": 9 },
                        { "P": [0.585, 0.585], "I": 21 },
                        { "P": [0.585, 0.585], "I": 33, "T": 0 },
                        { "P": [1, 1], "I": 34, "T": 0 }
                    ]
                ],
                [
                    "Alpha",
                    3035393,
                    [
                        { "V": 0, "I": 0, "T": 0 },
                        { "V": 0, "I": 9 },
                        { "V": 255, "I": 21 },
                        { "V": 0, "I": 33, "T": 0 },
                        { "V": 0, "I": 34, "T": 0 }
                    ]
                ],
                [
                    "P",
                    3035391,
                    [
                        { "P": [195.9, -32], "I": 0 },
                        { "P": [147.2, -32], "I": 6 },
                        { "P": [99.1, -32], "I": 15, "T": 0 },
                        { "P": [32, -32], "I": 16, "T": 0 },
                        { "P": [32, -32], "I": 19, "T": 0 }
                    ]
                ],
                [
                    "Scale",
                    3035391,
                    [
                        { "P": [0.0901, 2.4], "I": 0 },
                        { "P": [1.2258, 0.6], "I": 6 },
                        { "P": [0.0215, 0.1434], "I": 15, "T": 0 },
                        { "P": [1, 1], "I": 16, "T": 0 },
                        { "P": [1, 1], "I": 19, "T": 0 }
                    ]
                ],
                [
                    "Alpha",
                    3035391,
                    [
                        { "V": 255, "I": 0 },
                        { "V": 255, "I": 6 },
                        { "V": 255, "I": 15, "T": 0 },
                        { "V": 0, "I": 16, "T": 0 },
                        { "V": 0, "I": 19, "T": 0 }
                    ]
                ],
                [
                    "P",
                    3035389,
                    [
                        { "P": [140.5, -30.35], "I": 0, "T": 0 },
                        { "P": [140.5, -30.35], "I": 204, "T": 0 },
                        { "P": [140.5, -30.35], "I": 244, "T": 0 }
                    ]
                ],
                [
                    "Alpha",
                    3035389,
                    [
                        { "V": 0, "I": 0, "T": 0 },
                        { "V": 255, "I": 204, "T": 0 },
                        { "V": 255, "I": 244, "T": 0 }
                    ]
                ],
                [
                    "ActionValue",
                    3035387,
                    [
                        { "I": 0, "T": "BlankFrame" },
                        { "I": 159 },
                        { "I": 204, "T": "BlankFrame" }
                    ]
                ],
                [
                    "P",
                    3035387,
                    [
                        { "P": [140.75, -31], "I": 0, "T": 0 },
                        { "P": [140.75, -31], "I": 159, "T": 0 },
                        { "P": [31, -31], "I": 204, "T": 0 }
                    ]
                ],
                [
                    "Alpha",
                    3035387,
                    [
                        { "V": 0, "I": 0, "T": 0 },
                        { "V": 255, "I": 159, "T": 0 },
                        { "V": 0, "I": 204, "T": 0 }
                    ]
                ]
            ]
        },
        "D": {
            "C": [
                {
                    "F": [
                        1,
                        "gameScene/newshellgray.png",
                        "cocos/gameScene@6x"
                    ],
                    "Pos": [140, -30, 0.9, 0.9, 48, 41.6, 0, 0, 0.4896, 0.5264],
                    "Tag": 3035394,
                    "@": 3035395,
                    "A": 0,
                    "#": "layer5",
                    "$": "S"
                },
                {
                    "F": [1, "gameScene/newshell.png", "cocos/gameScene@6x"],
                    "Pos": [
                        170, -30, 0.585, 0.585, 68.8, 60.8, 0, 0, 0.4993, 0.5164
                    ],
                    "Tag": 3035392,
                    "@": 3035393,
                    "A": 0,
                    "#": "layer4",
                    "$": "S"
                },
                {
                    "F": [1, "gameScene/lightlinesp.png", "cocos/gameScene@6x"],
                    "Pos": [
                        195, -32, 0.0901, 2.4, 81.6, 9.6, 0, 0, 0.4963, 0.5
                    ],
                    "Tag": 3035390,
                    "@": 3035391,
                    "#": "layer3",
                    "$": "S"
                },
                {
                    "F": [1, "gameScene/newshell.png", "cocos/gameScene@6x"],
                    "Pos": [
                        140, -30, 0.585, 0.585, 68.8, 60.8, 0, 0, 0.4993, 0.5164
                    ],
                    "Tag": 3035388,
                    "@": 3035389,
                    "A": 0,
                    "#": "layer2",
                    "$": "S"
                },
                {
                    "F": [0, "cocos/gameScene_star_three_shell@6x.json", ""],
                    "Pos": [140, -31, 1, 1, 0, 0, 0, 0, 0, 0],
                    "CustomSizeEnabled": false,
                    "Tag": 3035386,
                    "@": 3035387,
                    "A": 0,
                    "#": "layer1",
                    "$": "PN"
                }
            ],
            "Size": { "X": 0, "Y": 0 },
            "$": "N"
        }
    },
    "Type": "Node"
}
