{
    "V": 2,
    "C": {
        "A": {
            "D": 15,
            "T": [
                [
                    "P",
                    3461522,
                    [
                        { "P": [5.85, -17.55], "I": 0 },
                        { "P": [5.85, -10.55], "I": 2 },
                        { "P": [1.3, -21.75], "I": 6, "T": 0 },
                        { "P": [1.3, -21.75], "I": 14, "T": 0 }
                    ]
                ],
                [
                    "Scale",
                    3461522,
                    [
                        { "P": [1.2, 1.2], "I": 0 },
                        { "P": [0.75, 0.75], "I": 2 },
                        { "P": [1.2, 1.2], "I": 6, "T": 0 },
                        { "P": [1.2, 1.2], "I": 14, "T": 0 }
                    ]
                ],
                [
                    "Alpha",
                    3461522,
                    [
                        { "V": 255, "I": 0 },
                        { "V": 255, "I": 2 },
                        { "V": 0, "I": 6, "T": 0 },
                        { "V": 0, "I": 14, "T": 0 }
                    ]
                ],
                [
                    "P",
                    3461520,
                    [
                        { "P": [1.3, 0.85], "I": 0 },
                        { "P": [1.3, 0.85], "I": 10 },
                        { "P": [-0.85, 0.85], "I": 11, "T": 0 }
                    ]
                ],
                [
                    "Scale",
                    3461520,
                    [
                        { "P": [0.9, 0.9], "I": 0 },
                        { "P": [0.2813, 0.2813], "I": 10 },
                        { "P": [1, 1], "I": 11, "T": 0 }
                    ]
                ],
                [
                    "Alpha",
                    3461520,
                    [
                        { "V": 173, "I": 0 },
                        { "V": 0, "I": 10 },
                        { "V": 0, "I": 11, "T": 0 }
                    ]
                ],
                [
                    "P",
                    3461518,
                    [
                        { "P": [-3.45, -10.05], "I": 0 },
                        { "P": [-1.15, -9.2], "I": 3 },
                        { "P": [-3.45, -10.05], "I": 8 },
                        { "P": [-3.45, -10.05], "I": 12, "T": 0 },
                        { "P": [-3.45, -10.05], "I": 14, "T": 0 }
                    ]
                ],
                [
                    "Scale",
                    3461518,
                    [
                        { "P": [0.9425, 0.9425], "I": 0 },
                        { "P": [0.7, 0.7], "I": 3 },
                        { "P": [1.0264, 1.0264], "I": 8 },
                        { "P": [0.8189, 0.8189], "I": 12, "T": 0 },
                        { "P": [0.8189, 0.8189], "I": 14, "T": 0 }
                    ]
                ],
                [
                    "P",
                    3461516,
                    [
                        { "P": [0.6, 3.55], "I": 0 },
                        { "P": [3.05, 2.2], "I": 2 },
                        { "P": [2.7, 2.5], "I": 5 },
                        { "P": [2.05, 3.1], "I": 7, "T": 0 },
                        { "P": [-3.1, 3.1], "I": 8, "T": 0 }
                    ]
                ],
                [
                    "Scale",
                    3461516,
                    [
                        { "P": [1.2, 1.2], "I": 0 },
                        { "P": [0.7542, 0.7542], "I": 2 },
                        { "P": [1.2166, 1.2166], "I": 5 },
                        { "P": [1.2445, 1.2445], "I": 7, "T": 0 },
                        { "P": [1, 1], "I": 8, "T": 0 }
                    ]
                ],
                [
                    "Alpha",
                    3461516,
                    [
                        { "V": 255, "I": 0 },
                        { "V": 255, "I": 2 },
                        { "V": 255, "I": 5 },
                        { "V": 0, "I": 7, "T": 0 },
                        { "V": 0, "I": 8, "T": 0 }
                    ]
                ],
                [
                    "P",
                    3461514,
                    [
                        { "P": [-3.45, 4.45], "I": 0 },
                        { "P": [-1.15, 2.95], "I": 3 },
                        { "P": [-3.45, 4.45], "I": 6 },
                        { "P": [-3.45, 4.45], "I": 9, "T": 0 },
                        { "P": [-3.45, 4.45], "I": 14, "T": 0 }
                    ]
                ],
                [
                    "Scale",
                    3461514,
                    [
                        { "P": [1, 1], "I": 0 },
                        { "P": [0.72, 0.72], "I": 3 },
                        { "P": [1.2, 1.2], "I": 6 },
                        { "P": [1, 1], "I": 9, "T": 0 },
                        { "P": [1, 1], "I": 14, "T": 0 }
                    ]
                ],
                [
                    "P",
                    3461512,
                    [
                        { "P": [62.65, 33.5], "I": 0, "T": 0 },
                        { "P": [62.65, 33.5], "I": 5 },
                        { "P": [71.55, 37.7], "I": 8 },
                        { "P": [77.55, 40.9], "I": 12 },
                        { "P": [-40.9, 40.9], "I": 13, "T": 0 }
                    ]
                ],
                [
                    "Scale",
                    3461512,
                    [
                        { "P": [0.1518, 0.1518], "I": 0, "T": 0 },
                        { "P": [0.1518, 0.1518], "I": 5 },
                        { "P": [0.1518, 0.1518], "I": 8 },
                        { "P": [0.1518, 0.1518], "I": 12 },
                        { "P": [1, 1], "I": 13, "T": 0 }
                    ]
                ],
                [
                    "Alpha",
                    3461512,
                    [
                        { "V": 0, "I": 0, "T": 0 },
                        { "V": 255, "I": 5 },
                        { "V": 255, "I": 8 },
                        { "V": 0, "I": 12 },
                        { "V": 0, "I": 13, "T": 0 }
                    ]
                ],
                [
                    "P",
                    3461510,
                    [
                        { "P": [-10.45, 68], "I": 0, "T": 0 },
                        { "P": [-10.45, 68], "I": 5 },
                        { "P": [-15.25, 82.8], "I": 8 },
                        { "P": [-16.85, 90.8], "I": 12 },
                        { "P": [-90.8, 90.8], "I": 13, "T": 0 }
                    ]
                ],
                [
                    "Scale",
                    3461510,
                    [
                        { "P": [0.1417, 0.1417], "I": 0, "T": 0 },
                        { "P": [0.1417, 0.1417], "I": 5 },
                        { "P": [0.1417, 0.1417], "I": 8 },
                        { "P": [0.1417, 0.1417], "I": 12 },
                        { "P": [1, 1], "I": 13, "T": 0 }
                    ]
                ],
                [
                    "Alpha",
                    3461510,
                    [
                        { "V": 0, "I": 0, "T": 0 },
                        { "V": 255, "I": 5 },
                        { "V": 255, "I": 8 },
                        { "V": 0, "I": 12 },
                        { "V": 0, "I": 13, "T": 0 }
                    ]
                ],
                [
                    "P",
                    3461508,
                    [
                        { "P": [-10.95, -65.1], "I": 0, "T": 0 },
                        { "P": [-10.95, -65.1], "I": 5 },
                        { "P": [-11.7, -77.35], "I": 8 },
                        { "P": [-14.1, -84.95], "I": 12 },
                        { "P": [84.95, -84.95], "I": 13, "T": 0 }
                    ]
                ],
                [
                    "Scale",
                    3461508,
                    [
                        { "P": [0.135, 0.135], "I": 0, "T": 0 },
                        { "P": [0.135, 0.135], "I": 5 },
                        { "P": [0.135, 0.135], "I": 8 },
                        { "P": [0.135, 0.135], "I": 12 },
                        { "P": [1, 1], "I": 13, "T": 0 }
                    ]
                ],
                [
                    "Alpha",
                    3461508,
                    [
                        { "V": 0, "I": 0, "T": 0 },
                        { "V": 255, "I": 5 },
                        { "V": 255, "I": 8 },
                        { "V": 0, "I": 12 },
                        { "V": 0, "I": 13, "T": 0 }
                    ]
                ],
                [
                    "P",
                    3461506,
                    [
                        { "P": [-41.55, -53.85], "I": 0, "T": 0 },
                        { "P": [-41.55, -53.85], "I": 5 },
                        { "P": [-49.75, -64.15], "I": 8 },
                        { "P": [-56.8, -72.95], "I": 12, "T": 0 },
                        { "P": [72.95, -72.95], "I": 13, "T": 0 }
                    ]
                ],
                [
                    "Scale",
                    3461506,
                    [
                        { "P": [0.135, 0.135], "I": 0, "T": 0 },
                        { "P": [0.135, 0.135], "I": 5 },
                        { "P": [0.135, 0.135], "I": 8 },
                        { "P": [0.135, 0.135], "I": 12, "T": 0 },
                        { "P": [1, 1], "I": 13, "T": 0 }
                    ]
                ],
                [
                    "Alpha",
                    3461506,
                    [
                        { "V": 0, "I": 0, "T": 0 },
                        { "V": 255, "I": 5 },
                        { "V": 255, "I": 8 },
                        { "V": 0, "I": 12, "T": 0 },
                        { "V": 0, "I": 13, "T": 0 }
                    ]
                ],
                [
                    "P",
                    3461504,
                    [
                        { "P": [-58.6, 33.15], "I": 0, "T": 0 },
                        { "P": [-58.6, 33.15], "I": 5 },
                        { "P": [-68.1, 38.05], "I": 8 },
                        { "P": [-79.3, 44.35], "I": 12 },
                        { "P": [-44.35, 44.35], "I": 13, "T": 0 }
                    ]
                ],
                [
                    "Scale",
                    3461504,
                    [
                        { "P": [0.1469, 0.1469], "I": 0, "T": 0 },
                        { "P": [0.1469, 0.1469], "I": 5 },
                        { "P": [0.1469, 0.1469], "I": 8 },
                        { "P": [0.1469, 0.1469], "I": 12 },
                        { "P": [1, 1], "I": 13, "T": 0 }
                    ]
                ],
                [
                    "Alpha",
                    3461504,
                    [
                        { "V": 0, "I": 0, "T": 0 },
                        { "V": 255, "I": 5 },
                        { "V": 255, "I": 8 },
                        { "V": 0, "I": 12 },
                        { "V": 0, "I": 13, "T": 0 }
                    ]
                ],
                [
                    "P",
                    3461502,
                    [
                        { "P": [-40.7, 54.8], "I": 0, "T": 0 },
                        { "P": [-40.7, 54.8], "I": 5 },
                        { "P": [-48.3, 66], "I": 8 },
                        { "P": [-55.1, 74], "I": 12, "T": 0 },
                        { "P": [-74, 74], "I": 13, "T": 0 }
                    ]
                ],
                [
                    "Scale",
                    3461502,
                    [
                        { "P": [0.1469, 0.1469], "I": 0, "T": 0 },
                        { "P": [0.1469, 0.1469], "I": 5 },
                        { "P": [0.1469, 0.1469], "I": 8 },
                        { "P": [0.1469, 0.1469], "I": 12, "T": 0 },
                        { "P": [1, 1], "I": 13, "T": 0 }
                    ]
                ],
                [
                    "Alpha",
                    3461502,
                    [
                        { "V": 0, "I": 0, "T": 0 },
                        { "V": 255, "I": 5 },
                        { "V": 255, "I": 8 },
                        { "V": 0, "I": 12, "T": 0 },
                        { "V": 0, "I": 13, "T": 0 }
                    ]
                ],
                [
                    "P",
                    3461500,
                    [
                        { "P": [-65.4, 3.4], "I": 0, "T": 0 },
                        { "P": [-65.4, 3.4], "I": 5 },
                        { "P": [-79.8, 3.4], "I": 8 },
                        { "P": [-91.8, 3.4], "I": 12 },
                        { "P": [-3.4, 3.4], "I": 13, "T": 0 }
                    ]
                ],
                [
                    "Scale",
                    3461500,
                    [
                        { "P": [0.1469, 0.1469], "I": 0, "T": 0 },
                        { "P": [0.1469, 0.1469], "I": 5 },
                        { "P": [0.1469, 0.1469], "I": 8 },
                        { "P": [0.1469, 0.1469], "I": 12 },
                        { "P": [1, 1], "I": 13, "T": 0 }
                    ]
                ],
                [
                    "Alpha",
                    3461500,
                    [
                        { "V": 0, "I": 0, "T": 0 },
                        { "V": 255, "I": 5 },
                        { "V": 255, "I": 8 },
                        { "V": 0, "I": 12 },
                        { "V": 0, "I": 13, "T": 0 }
                    ]
                ],
                [
                    "P",
                    3461498,
                    [
                        { "P": [50.5, -48.7], "I": 0, "T": 0 },
                        { "P": [50.5, -48.7], "I": 5 },
                        { "P": [60.9, -60.55], "I": 8 },
                        { "P": [65.3, -66.55], "I": 12 },
                        { "P": [66.55, -66.55], "I": 13, "T": 0 }
                    ]
                ],
                [
                    "Scale",
                    3461498,
                    [
                        { "P": [0.1334, 0.1334], "I": 0, "T": 0 },
                        { "P": [0.1334, 0.1334], "I": 5 },
                        { "P": [0.1334, 0.1334], "I": 8 },
                        { "P": [0.1334, 0.1334], "I": 12 },
                        { "P": [1, 1], "I": 13, "T": 0 }
                    ]
                ],
                [
                    "Alpha",
                    3461498,
                    [
                        { "V": 0, "I": 0, "T": 0 },
                        { "V": 255, "I": 5 },
                        { "V": 255, "I": 8 },
                        { "V": 0, "I": 12 },
                        { "V": 0, "I": 13, "T": 0 }
                    ]
                ],
                [
                    "P",
                    3461496,
                    [
                        { "P": [67.2, -23.85], "I": 0, "T": 0 },
                        { "P": [67.2, -23.85], "I": 5 },
                        { "P": [80.5, -30.25], "I": 8 },
                        { "P": [87.4, -35.05], "I": 12, "T": 0 },
                        { "P": [35.05, -35.05], "I": 13, "T": 0 }
                    ]
                ],
                [
                    "Scale",
                    3461496,
                    [
                        { "P": [0.1334, 0.1334], "I": 0, "T": 0 },
                        { "P": [0.1334, 0.1334], "I": 5 },
                        { "P": [0.1334, 0.1334], "I": 8 },
                        { "P": [0.1334, 0.1334], "I": 12, "T": 0 },
                        { "P": [1, 1], "I": 13, "T": 0 }
                    ]
                ],
                [
                    "Alpha",
                    3461496,
                    [
                        { "V": 0, "I": 0, "T": 0 },
                        { "V": 255, "I": 5 },
                        { "V": 255, "I": 8 },
                        { "V": 0, "I": 12, "T": 0 },
                        { "V": 0, "I": 13, "T": 0 }
                    ]
                ],
                [
                    "P",
                    3461494,
                    [
                        { "P": [70.1, 5.2], "I": 0, "T": 0 },
                        { "P": [70.1, 5.2], "I": 5 },
                        { "P": [84.7, 5], "I": 8 },
                        { "P": [91.9, 5], "I": 12, "T": 0 },
                        { "P": [-5, 5], "I": 13, "T": 0 }
                    ]
                ],
                [
                    "Scale",
                    3461494,
                    [
                        { "P": [0.1334, 0.1334], "I": 0, "T": 0 },
                        { "P": [0.1334, 0.1334], "I": 5 },
                        { "P": [0.1334, 0.1334], "I": 8 },
                        { "P": [0.1334, 0.1334], "I": 12, "T": 0 },
                        { "P": [1, 1], "I": 13, "T": 0 }
                    ]
                ],
                [
                    "Alpha",
                    3461494,
                    [
                        { "V": 0, "I": 0, "T": 0 },
                        { "V": 255, "I": 5 },
                        { "V": 255, "I": 8 },
                        { "V": 0, "I": 12, "T": 0 },
                        { "V": 0, "I": 13, "T": 0 }
                    ]
                ],
                [
                    "P",
                    3461492,
                    [
                        { "P": [23.95, -63.9], "I": 0, "T": 0 },
                        { "P": [23.95, -63.9], "I": 5 },
                        { "P": [27.85, -76.25], "I": 8 },
                        { "P": [30.15, -83.9], "I": 12 },
                        { "P": [83.9, -83.9], "I": 13, "T": 0 }
                    ]
                ],
                [
                    "Scale",
                    3461492,
                    [
                        { "P": [0.1334, 0.1334], "I": 0, "T": 0 },
                        { "P": [0.1334, 0.1334], "I": 5 },
                        { "P": [0.1334, 0.1334], "I": 8 },
                        { "P": [0.1334, 0.1334], "I": 12 },
                        { "P": [1, 1], "I": 13, "T": 0 }
                    ]
                ],
                [
                    "Alpha",
                    3461492,
                    [
                        { "V": 0, "I": 0, "T": 0 },
                        { "V": 255, "I": 5 },
                        { "V": 255, "I": 8 },
                        { "V": 0, "I": 12 },
                        { "V": 0, "I": 13, "T": 0 }
                    ]
                ],
                [
                    "P",
                    3461490,
                    [
                        { "P": [43.75, 55.65], "I": 0, "T": 0 },
                        { "P": [43.75, 55.65], "I": 5 },
                        { "P": [51.15, 64.55], "I": 8 },
                        { "P": [56.35, 70.55], "I": 12 },
                        { "P": [-70.55, 70.55], "I": 13, "T": 0 }
                    ]
                ],
                [
                    "Scale",
                    3461490,
                    [
                        { "P": [0.1491, 0.1491], "I": 0, "T": 0 },
                        { "P": [0.1491, 0.1491], "I": 5 },
                        { "P": [0.1491, 0.1491], "I": 8 },
                        { "P": [0.1491, 0.1491], "I": 12 },
                        { "P": [1, 1], "I": 13, "T": 0 }
                    ]
                ],
                [
                    "Alpha",
                    3461490,
                    [
                        { "V": 0, "I": 0, "T": 0 },
                        { "V": 255, "I": 5 },
                        { "V": 255, "I": 8 },
                        { "V": 0, "I": 12 },
                        { "V": 0, "I": 13, "T": 0 }
                    ]
                ],
                [
                    "P",
                    3461488,
                    [
                        { "P": [18.2, 69.7], "I": 0, "T": 0 },
                        { "P": [18.2, 69.7], "I": 5 },
                        { "P": [21.9, 82.5], "I": 8 },
                        { "P": [24.3, 89.7], "I": 12 },
                        { "P": [-89.7, 89.7], "I": 13, "T": 0 }
                    ]
                ],
                [
                    "Scale",
                    3461488,
                    [
                        { "P": [0.1419, 0.1419], "I": 0, "T": 0 },
                        { "P": [0.1419, 0.1419], "I": 5 },
                        { "P": [0.1419, 0.1419], "I": 8 },
                        { "P": [0.1419, 0.1419], "I": 12 },
                        { "P": [1, 1], "I": 13, "T": 0 }
                    ]
                ],
                [
                    "Alpha",
                    3461488,
                    [
                        { "V": 0, "I": 0, "T": 0 },
                        { "V": 255, "I": 5 },
                        { "V": 255, "I": 8 },
                        { "V": 0, "I": 12 },
                        { "V": 0, "I": 13, "T": 0 }
                    ]
                ],
                [
                    "P",
                    3461486,
                    [
                        { "P": [-59.9, -28.05], "I": 0, "T": 0 },
                        { "P": [-59.9, -28.05], "I": 5 },
                        { "P": [-71.7, -32.1], "I": 8 },
                        { "P": [-87.7, -41.7], "I": 12 },
                        { "P": [41.7, -41.7], "I": 13, "T": 0 }
                    ]
                ],
                [
                    "Scale",
                    3461486,
                    [
                        { "P": [0.1469, 0.1469], "I": 0, "T": 0 },
                        { "P": [0.1469, 0.1469], "I": 5 },
                        { "P": [0.1469, 0.1469], "I": 8 },
                        { "P": [0.1469, 0.1469], "I": 12 },
                        { "P": [1, 1], "I": 13, "T": 0 }
                    ]
                ],
                [
                    "Alpha",
                    3461486,
                    [
                        { "V": 0, "I": 0, "T": 0 },
                        { "V": 255, "I": 5 },
                        { "V": 255, "I": 8 },
                        { "V": 0, "I": 12 },
                        { "V": 0, "I": 13, "T": 0 }
                    ]
                ],
                [
                    "P",
                    3461484,
                    [
                        { "P": [-52.95, 37.6], "I": 0 },
                        { "P": [-35.35, 24.7], "I": 3 },
                        { "P": [-54.35, 36.8], "I": 7, "T": 0 },
                        { "P": [-36.8, 36.8], "I": 8, "T": 0 }
                    ]
                ],
                [
                    "Scale",
                    3461484,
                    [
                        { "P": [0.3906, 0.4227], "I": 0 },
                        { "P": [0.2935, 0.3177], "I": 3 },
                        { "P": [0.4281, 0.4632], "I": 7, "T": 0 },
                        { "P": [1, 1], "I": 8, "T": 0 }
                    ]
                ],
                [
                    "R",
                    3461484,
                    [
                        { "P": [-32.17, 0], "I": 0 },
                        { "P": [-32.17, 0], "I": 3 },
                        { "P": [-32.17, 0], "I": 7, "T": 0 },
                        { "I": 8, "T": 0 }
                    ]
                ],
                [
                    "Alpha",
                    3461484,
                    [
                        { "V": 255, "I": 0 },
                        { "V": 255, "I": 3 },
                        { "V": 0, "I": 7, "T": 0 },
                        { "V": 0, "I": 8, "T": 0 }
                    ]
                ],
                [
                    "P",
                    3461482,
                    [
                        { "P": [-24, 36], "I": 0 },
                        { "P": [-18.25, 29.05], "I": 1 },
                        { "P": [-13.6, 23.5], "I": 3 },
                        { "P": [-22.5, 35.05], "I": 7, "T": 0 },
                        { "P": [-35.05, 35.05], "I": 8, "T": 0 }
                    ]
                ],
                [
                    "Scale",
                    3461482,
                    [
                        { "P": [1.4444, 1], "I": 0 },
                        { "P": [1.2433, 0.8608], "I": 1 },
                        { "P": [1.0854, 0.7514], "I": 3 },
                        { "P": [1.5829, 1.0959], "I": 7, "T": 0 },
                        { "P": [1, 1], "I": 8, "T": 0 }
                    ]
                ],
                [
                    "R",
                    3461482,
                    [
                        { "P": [-27.99, -27.99], "I": 0 },
                        { "P": [-27.85, -27.85], "I": 1 },
                        { "P": [-27.99, -27.99], "I": 3 },
                        { "P": [-27.99, -27.99], "I": 7, "T": 0 },
                        { "I": 8, "T": 0 }
                    ]
                ],
                [
                    "Alpha",
                    3461482,
                    [
                        { "V": 255, "I": 0 },
                        { "V": 255, "I": 1 },
                        { "V": 255, "I": 3 },
                        { "V": 0, "I": 7, "T": 0 },
                        { "V": 0, "I": 8, "T": 0 }
                    ]
                ],
                [
                    "P",
                    3461480,
                    [
                        { "P": [34.45, -38.75], "I": 0 },
                        { "P": [30.35, -32.65], "I": 3 },
                        { "P": [41.55, -46.85], "I": 7, "T": 0 },
                        { "P": [46.85, -46.85], "I": 8, "T": 0 }
                    ]
                ],
                [
                    "Scale",
                    3461480,
                    [
                        { "P": [1, 1], "I": 0 },
                        { "P": [0.7514, 0.7514], "I": 3 },
                        { "P": [1.0959, 1.0959], "I": 7, "T": 0 },
                        { "P": [1, 1], "I": 8, "T": 0 }
                    ]
                ],
                [
                    "R",
                    3461480,
                    [
                        { "P": [6.19, 6.19], "I": 0 },
                        { "P": [6.19, 6.19], "I": 3 },
                        { "P": [6.19, 6.19], "I": 7, "T": 0 },
                        { "I": 8, "T": 0 }
                    ]
                ],
                [
                    "Alpha",
                    3461480,
                    [
                        { "V": 255, "I": 0 },
                        { "V": 255, "I": 3 },
                        { "V": 0, "I": 7, "T": 0 },
                        { "V": 0, "I": 8, "T": 0 }
                    ]
                ],
                [
                    "P",
                    3461478,
                    [
                        { "P": [-34.05, 54.45], "I": 0 },
                        { "P": [-21.15, 37.35], "I": 3 },
                        { "P": [-33.55, 55.35], "I": 7, "T": 0 },
                        { "P": [-55.35, 55.35], "I": 8, "T": 0 }
                    ]
                ],
                [
                    "Scale",
                    3461478,
                    [
                        { "P": [1, 1], "I": 0 },
                        { "P": [0.7514, 0.7514], "I": 3 },
                        { "P": [1.0959, 1.0959], "I": 7, "T": 0 },
                        { "P": [1, 1], "I": 8, "T": 0 }
                    ]
                ],
                [
                    "R",
                    3461478,
                    [
                        { "P": [6.23, 6.23], "I": 0 },
                        { "P": [6.23, 6.23], "I": 3 },
                        { "P": [6.23, 6.23], "I": 7, "T": 0 },
                        { "I": 8, "T": 0 }
                    ]
                ],
                [
                    "Alpha",
                    3461478,
                    [
                        { "V": 255, "I": 0 },
                        { "V": 255, "I": 3 },
                        { "V": 0, "I": 7, "T": 0 },
                        { "V": 0, "I": 8, "T": 0 }
                    ]
                ],
                [
                    "P",
                    3461476,
                    [
                        { "P": [44.65, -24.4], "I": 0, "T": 0 },
                        { "P": [44.65, -24.4], "I": 1 },
                        { "P": [44.65, -24.4], "I": 4 },
                        { "P": [44.65, -24.4], "I": 8, "T": 0 },
                        { "P": [44.65, -24.4], "I": 14, "T": 0 }
                    ]
                ],
                [
                    "Scale",
                    3461476,
                    [
                        { "P": [1.3641, 1.3641], "I": 0, "T": 0 },
                        { "P": [1.3641, 1.3641], "I": 1 },
                        { "P": [0.6649, 0.6649], "I": 4 },
                        { "P": [1, 1], "I": 8, "T": 0 },
                        { "P": [1, 1], "I": 14, "T": 0 }
                    ]
                ],
                [
                    "Alpha",
                    3461476,
                    [
                        { "V": 0, "I": 0, "T": 0 },
                        { "V": 0, "I": 1 },
                        { "V": 255, "I": 4 },
                        { "V": 255, "I": 8, "T": 0 },
                        { "V": 255, "I": 14, "T": 0 }
                    ]
                ]
            ]
        },
        "D": {
            "C": [
                {
                    "F": [
                        1,
                        "uilibrary/startuishadownew.png",
                        "cocos/uilibrary@6x"
                    ],
                    "Pos": [
                        5, -17, 1.2, 1.2, 124.8, 124.8, 0, 0, 0.4972, 0.5028
                    ],
                    "Tag": 3461521,
                    "@": 3461522,
                    "#": "startuishadownew",
                    "$": "S"
                },
                {
                    "F": [
                        1,
                        "uilibrary/mc_bubble_under2.png",
                        "cocos/uilibrary@6x"
                    ],
                    "Pos": [1, 0, 0.9, 0.9, 166.4, 166.4, 0, 0, 0.4895, 0.5105],
                    "Tag": 3461519,
                    "@": 3461520,
                    "A": 173,
                    "#": "bubbleshadow",
                    "$": "S"
                },
                {
                    "F": [
                        1,
                        "uilibrary/iconplaceholder.png",
                        "cocos/uilibrary@6x"
                    ],
                    "Pos": [
                        -3, -10, 0.9425, 0.9425, 100.8, 100.8, 0, 0, 0.497,
                        0.503
                    ],
                    "Tag": 3461517,
                    "@": 3461518,
                    "#": "daoju_shadow",
                    "$": "S"
                },
                {
                    "F": [
                        1,
                        "uilibrary/mc_bubble_under.png",
                        "cocos/uilibrary@6x"
                    ],
                    "Pos": [0, 3, 1.2, 1.2, 147.2, 155.2, 0, 0, 0.5003, 0.5061],
                    "Tag": 3461515,
                    "@": 3461516,
                    "#": "under",
                    "$": "S"
                },
                {
                    "F": [
                        1,
                        "uilibrary/iconplaceholder.png",
                        "cocos/uilibrary@6x"
                    ],
                    "Pos": [-3, 4, 1, 1, 100.8, 100.8, 0, 0, 0.497, 0.503],
                    "Tag": 3461513,
                    "@": 3461514,
                    "#": "daoju",
                    "$": "S"
                },
                {
                    "F": [
                        1,
                        "uilibrary/mc_bomb_bubble.png",
                        "cocos/uilibrary@6x"
                    ],
                    "Pos": [
                        62, 33, 0.1518, 0.1518, 150.4, 161.6, 0, 0, 0.4897,
                        0.5136
                    ],
                    "Tag": 3461511,
                    "@": 3461512,
                    "#": "b13",
                    "$": "S"
                },
                {
                    "F": [
                        1,
                        "uilibrary/mc_bomb_bubble.png",
                        "cocos/uilibrary@6x"
                    ],
                    "Pos": [
                        -10, 68, 0.1417, 0.1417, 150.4, 161.6, 0, 0, 0.4897,
                        0.5136
                    ],
                    "Tag": 3461509,
                    "@": 3461510,
                    "#": "b14",
                    "$": "S"
                },
                {
                    "F": [
                        1,
                        "uilibrary/mc_bomb_bubble.png",
                        "cocos/uilibrary@6x"
                    ],
                    "Pos": [
                        -10, -65, 0.135, 0.135, 150.4, 161.6, 0, 0, 0.4897,
                        0.5136
                    ],
                    "Tag": 3461507,
                    "@": 3461508,
                    "#": "b12",
                    "$": "S"
                },
                {
                    "F": [
                        1,
                        "uilibrary/mc_bomb_bubble.png",
                        "cocos/uilibrary@6x"
                    ],
                    "Pos": [
                        -41, -53, 0.135, 0.135, 150.4, 161.6, 0, 0, 0.4897,
                        0.5136
                    ],
                    "Tag": 3461505,
                    "@": 3461506,
                    "#": "b11",
                    "$": "S"
                },
                {
                    "F": [
                        1,
                        "uilibrary/mc_bomb_bubble.png",
                        "cocos/uilibrary@6x"
                    ],
                    "Pos": [
                        -58, 33, 0.1469, 0.1469, 150.4, 161.6, 0, 0, 0.4897,
                        0.5136
                    ],
                    "Tag": 3461503,
                    "@": 3461504,
                    "#": "b10",
                    "$": "S"
                },
                {
                    "F": [
                        1,
                        "uilibrary/mc_bomb_bubble.png",
                        "cocos/uilibrary@6x"
                    ],
                    "Pos": [
                        -40, 54, 0.1469, 0.1469, 150.4, 161.6, 0, 0, 0.4897,
                        0.5136
                    ],
                    "Tag": 3461501,
                    "@": 3461502,
                    "#": "b9",
                    "$": "S"
                },
                {
                    "F": [
                        1,
                        "uilibrary/mc_bomb_bubble.png",
                        "cocos/uilibrary@6x"
                    ],
                    "Pos": [
                        -65, 3, 0.1469, 0.1469, 150.4, 161.6, 0, 0, 0.4897,
                        0.5136
                    ],
                    "Tag": 3461499,
                    "@": 3461500,
                    "#": "b8",
                    "$": "S"
                },
                {
                    "F": [
                        1,
                        "uilibrary/mc_bomb_bubble.png",
                        "cocos/uilibrary@6x"
                    ],
                    "Pos": [
                        50, -48, 0.1334, 0.1334, 150.4, 161.6, 0, 0, 0.4897,
                        0.5136
                    ],
                    "Tag": 3461497,
                    "@": 3461498,
                    "#": "b7",
                    "$": "S"
                },
                {
                    "F": [
                        1,
                        "uilibrary/mc_bomb_bubble.png",
                        "cocos/uilibrary@6x"
                    ],
                    "Pos": [
                        67, -23, 0.1334, 0.1334, 150.4, 161.6, 0, 0, 0.4897,
                        0.5136
                    ],
                    "Tag": 3461495,
                    "@": 3461496,
                    "#": "b6",
                    "$": "S"
                },
                {
                    "F": [
                        1,
                        "uilibrary/mc_bomb_bubble.png",
                        "cocos/uilibrary@6x"
                    ],
                    "Pos": [
                        70, 5, 0.1334, 0.1334, 150.4, 161.6, 0, 0, 0.4897,
                        0.5136
                    ],
                    "Tag": 3461493,
                    "@": 3461494,
                    "#": "b5",
                    "$": "S"
                },
                {
                    "F": [
                        1,
                        "uilibrary/mc_bomb_bubble.png",
                        "cocos/uilibrary@6x"
                    ],
                    "Pos": [
                        23, -63, 0.1334, 0.1334, 150.4, 161.6, 0, 0, 0.4897,
                        0.5136
                    ],
                    "Tag": 3461491,
                    "@": 3461492,
                    "#": "b4",
                    "$": "S"
                },
                {
                    "F": [
                        1,
                        "uilibrary/mc_bomb_bubble.png",
                        "cocos/uilibrary@6x"
                    ],
                    "Pos": [
                        43, 55, 0.1491, 0.1491, 150.4, 161.6, 0, 0, 0.4897,
                        0.5136
                    ],
                    "Tag": 3461489,
                    "@": 3461490,
                    "#": "b3",
                    "$": "S"
                },
                {
                    "F": [
                        1,
                        "uilibrary/mc_bomb_bubble.png",
                        "cocos/uilibrary@6x"
                    ],
                    "Pos": [
                        18, 69, 0.1419, 0.1419, 150.4, 161.6, 0, 0, 0.4897,
                        0.5136
                    ],
                    "Tag": 3461487,
                    "@": 3461488,
                    "#": "b2",
                    "$": "S"
                },
                {
                    "F": [
                        1,
                        "uilibrary/mc_bomb_bubble.png",
                        "cocos/uilibrary@6x"
                    ],
                    "Pos": [
                        -59, -28, 0.1469, 0.1469, 150.4, 161.6, 0, 0, 0.4897,
                        0.5136
                    ],
                    "Tag": 3461485,
                    "@": 3461486,
                    "#": "b1",
                    "$": "S"
                },
                {
                    "F": [1, "uilibrary/mc_light1.png", "cocos/uilibrary@6x"],
                    "Pos": [
                        -52, 37, 0.3906, 0.4227, 72, 62.4, -32.17, 0, 0.4833,
                        0.5889
                    ],
                    "Tag": 3461483,
                    "@": 3461484,
                    "#": "l4",
                    "$": "S"
                },
                {
                    "F": [1, "uilibrary/mc_light2.png", "cocos/uilibrary@6x"],
                    "Pos": [
                        -24, 36, 1.4444, 1, 49.6, 49.6, -27.99, -27.99, 0.501,
                        0.499
                    ],
                    "Tag": 3461481,
                    "@": 3461482,
                    "#": "l3",
                    "$": "S"
                },
                {
                    "F": [1, "uilibrary/mc_light3.png", "cocos/uilibrary@6x"],
                    "Pos": [34, -38, 1, 1, 81.6, 72, 6.19, 6.19, 0.625, 0.4708],
                    "Tag": 3461479,
                    "@": 3461480,
                    "#": "l2",
                    "$": "S"
                },
                {
                    "F": [1, "uilibrary/mc_light1.png", "cocos/uilibrary@6x"],
                    "Pos": [
                        -34, 54, 1, 1, 72, 62.4, 6.23, 6.23, 0.4833, 0.5889
                    ],
                    "Tag": 3461477,
                    "@": 3461478,
                    "#": "light1",
                    "$": "S"
                },
                {
                    "F": [1, "uilibrary/nike_bottom.png", "cocos/uilibrary@6x"],
                    "Pos": [
                        44, -24, 1.3641, 1.3641, 83.2, 72, 0, 0, 0.494, 0.5056
                    ],
                    "Tag": 3461475,
                    "@": 3461476,
                    "A": 0,
                    "#": "nike",
                    "$": "S"
                }
            ],
            "Size": { "X": 0, "Y": 0 },
            "$": "N"
        }
    },
    "Type": "Node"
}
